odoo10_addon_website_sale_hide_empty_category-10.0.1.0.0-py2.7-nspkg.pth
odoo/addons/website_sale_hide_empty_category/README.rst
odoo/addons/website_sale_hide_empty_category/__init__.py
odoo/addons/website_sale_hide_empty_category/__manifest__.py
odoo/addons/website_sale_hide_empty_category/models/__init__.py
odoo/addons/website_sale_hide_empty_category/models/product_public_category.py
odoo/addons/website_sale_hide_empty_category/views/website_sale_templates.xml
odoo10_addon_website_sale_hide_empty_category-10.0.1.0.0.dist-info/DESCRIPTION.rst
odoo10_addon_website_sale_hide_empty_category-10.0.1.0.0.dist-info/METADATA
odoo10_addon_website_sale_hide_empty_category-10.0.1.0.0.dist-info/RECORD
odoo10_addon_website_sale_hide_empty_category-10.0.1.0.0.dist-info/WHEEL
odoo10_addon_website_sale_hide_empty_category-10.0.1.0.0.dist-info/metadata.json
odoo10_addon_website_sale_hide_empty_category-10.0.1.0.0.dist-info/namespace_packages.txt
odoo10_addon_website_sale_hide_empty_category-10.0.1.0.0.dist-info/top_level.txt
